Systolic_Array.v
module Processing_Element(A,B,Aout,Bout,clk,clr,read,write);
parameter N=32;
input[N-1:0] A,B;
output reg[N-1:0] Aout,Bout;
reg[N-1:0] Acc;
input clk,clr,read,write;
always @(posedge clk)begin
    if(clr & ~read & ~write)begin
        Acc<=0;
        Aout<=0;
        Bout<=0;
    end
    else if(~clr & read & ~write)begin
        Acc<=B;
    end
    else if(~clr & write & ~read)begin
        Bout<=Acc;
    end
    else if(~clr & write & read)begin
        Acc<=B;
        Bout<=Acc;
    end
    else begin
        Acc<=Acc+A*B;
        Aout<=A;
        Bout<=B;
    end
end
endmodule
module PE_layer(A0,B0,B1,B2,B3,B4,A0_out,B0_out,B1_out,B2_out,B3_out,B4_out,clk,clr,read,write);
parameter N=32;
parameter M=5;
input[N-1:0] A0,B0,B1,B2,B3,B4;
output[N-1:0] A0_out,B0_out,B1_out,B2_out,B3_out,B4_out;
input clk;
input[M-1:0] clr,read,write;
wire[N-1:0] A0_temp0,A0_temp1,A0_temp2,A0_temp3;
Processing_Element PE0(A0,B0,A0_temp0,B0_out,clk,clr[0],read[0],write[0]);
Processing_Element PE1(A0_temp0,B1,A0_temp1,B1_out,clk,clr[1],read[1],write[1]);
Processing_Element PE2(A0_temp1,B2,A0_temp2,B2_out,clk,clr[2],read[2],write[2]);
Processing_Element PE3(A0_temp2,B3,A0_temp3,B3_out,clk,clr[3],read[3],write[3]);
Processing_Element PE4(A0_temp3,B4,A0_out,B4_out,clk,clr[4],read[4],write[4]);
endmodule
module Systolic_Array(A0,A1,A2,A3,A4,B0,B1,B2,B3,B4,A0_out,A1_out,A2_out,A3_out,A4_out,B0_out,B1_out,B2_out,B3_out,B4_out,clk,clr,read,write);
parameter N=32;
parameter M=25;
input[N-1:0] A0,A1,A2,A3,A4,B0,B1,B2,B3,B4;
output[N-1:0] A0_out,A1_out,A2_out,A3_out,A4_out,B0_out,B1_out,B2_out,B3_out,B4_out;
input clk;
input[M-1:0] clr,read,write;
wire[N-1:0] B0_temp0,B1_temp0,B2_temp0,B3_temp0,B4_temp0;
wire[N-1:0] B0_temp1,B1_temp1,B2_temp1,B3_temp1,B4_temp1;
wire[N-1:0] B0_temp2,B1_temp2,B2_temp2,B3_temp2,B4_temp2;
wire[N-1:0] B0_temp3,B1_temp3,B2_temp3,B3_temp3,B4_temp3;
PE_layer PE_layer0(A0,B0,B1,B2,B3,B4,A0_out,B0_temp0,B1_temp0,B2_temp0,B3_temp0,B4_temp0,clk,clr[4:0],read[4:0],write[4:0]);
PE_layer PE_layer1(A1,B0_temp0,B1_temp0,B2_temp0,B3_temp0,B4_temp0,A1_out,B0_temp1,B1_temp1,B2_temp1,B3_temp1,B4_temp1,clk,clr[9:5],read[9:5],write[9:5]);
PE_layer PE_layer2(A2,B0_temp1,B1_temp1,B2_temp1,B3_temp1,B4_temp1,A2_out,B0_temp2,B1_temp2,B2_temp2,B3_temp2,B4_temp2,clk,clr[14:10],read[14:10],write[14:10]);
PE_layer PE_layer3(A3,B0_temp2,B1_temp2,B2_temp2,B3_temp2,B4_temp2,A3_out,B0_temp3,B1_temp3,B2_temp3,B3_temp3,B4_temp3,clk,clr[19:15],read[19:15],write[19:15]);
PE_layer PE_layer4(A4,B0_temp3,B1_temp3,B2_temp3,B3_temp3,B4_temp3,A4_out,B0_out,B1_out,B2_out,B3_out,B4_out,clk,clr[24:20],read[24:20],write[24:20]);
endmodule

Processing_Element_test.v
module Processing_Element_test;
parameter N=32;
reg read,write,clr,clk;
reg[N-1:0] A,B;
wire[N-1:0] Aout,Bout;
Processing_Element DUT(A,B,Aout,Bout,clk,clr,read,write);
initial begin
    clk=0;
    clr=1;
    read=0;
    write=0;
    A=5;B=2;
    #10 clr=0;
    #12 read=1;A=20;write=1;
    #10 read=0;write=0;
    #10 clr=1;
    #200 $finish;
end
always #5 clk=~clk;
initial begin
    $dumpfile("Processing_Element_test.vcd");
    $dumpvars(0,Processing_Element_test);
end
endmodule

Processing_Element_test.vcd
$date
	Wed Sep 14 11:35:47 2022
$end
$version
	Icarus Verilog
$end
$timescale
	1s
$end
$scope module Processing_Element_test $end
$var wire 32 ! Aout [31:0] $end
$var wire 32 " Bout [31:0] $end
$var reg 32 # A [31:0] $end
$var reg 32 $ B [31:0] $end
$var reg 1 % clk $end
$var reg 1 & clr $end
$var reg 1 ' read $end
$var reg 1 ( write $end
$scope module DUT $end
$var wire 32 ) A [31:0] $end
$var wire 32 * B [31:0] $end
$var wire 1 + clk $end
$var wire 1 , clr $end
$var wire 1 - read $end
$var wire 1 . write $end
$var reg 32 / Acc [31:0] $end
$var reg 32 0 Aout [31:0] $end
$var reg 32 1 Bout [31:0] $end
$upscope $end
$upscope $end
$enddefinitions $end
#0
$dumpvars
bx 1
bx 0
bx /
0.
0-
1,
0+
b10 *
b101 )
0(
0'
1&
0%
b10 $
b101 #
bx "
bx !
$end
#5
b0 1
b0 "
b0 0
b0 !
b0 /
1%
1+
#10
0%
0+
0&
0,
#15
b10 1
b10 "
b101 0
b101 !
b1010 /
1%
1+
#20
0%
0+
#22
1(
1.
b10100 #
b10100 )
1'
1-
#25
b1010 1
b1010 "
b10 /
1%
1+
#30
0%
0+
#32
0(
0.
0'
0-
#35
b10 1
b10 "
b10100 0
b10100 !
b101010 /
1%
1+
#40
0%
0+
#42
1&
1,
#45
b0 1
b0 "
b0 0
b0 !
b0 /
1%
1+
