Systolic_Array.v
module Processing_Element(A,B,Aout,Bout,clk,clr,read,write);
parameter N=32;
input[N-1:0] A,B;
output reg[N-1:0] Aout,Bout;
reg[N-1:0] Acc;
input clk,clr,read,write;
always @(posedge clk)begin
    if(clr & ~read & ~write)begin
        Acc<=0;
        Aout<=0;
        Bout<=0;
    end
    else if(~clr & read & ~write)begin
        Acc<=B;
    end
    else if(~clr & write & ~read)begin
        Bout<=Acc;
    end
    else if(~clr & write & read)begin
        Acc<=B;
        Bout<=Acc;
    end
    else begin
        Acc<=Acc+A*B;
        Aout<=A;
        Bout<=B;
    end
end
endmodule
module PE_layer(A0,B0,B1,B2,B3,B4,A0_out,B0_out,B1_out,B2_out,B3_out,B4_out,clk,clr,read,write);
parameter N=32;
parameter M=5;
input[N-1:0] A0,B0,B1,B2,B3,B4;
output[N-1:0] A0_out,B0_out,B1_out,B2_out,B3_out,B4_out;
input clk;
input[M-1:0] clr,read,write;
wire[N-1:0] A0_temp0,A0_temp1,A0_temp2,A0_temp3;
Processing_Element PE0(A0,B0,A0_temp0,B0_out,clk,clr[0],read[0],write[0]);
Processing_Element PE1(A0_temp0,B1,A0_temp1,B1_out,clk,clr[1],read[1],write[1]);
Processing_Element PE2(A0_temp1,B2,A0_temp2,B2_out,clk,clr[2],read[2],write[2]);
Processing_Element PE3(A0_temp2,B3,A0_temp3,B3_out,clk,clr[3],read[3],write[3]);
Processing_Element PE4(A0_temp3,B4,A0_out,B4_out,clk,clr[4],read[4],write[4]);
endmodule
module Systolic_Array(A0,A1,A2,A3,A4,B0,B1,B2,B3,B4,A0_out,A1_out,A2_out,A3_out,A4_out,B0_out,B1_out,B2_out,B3_out,B4_out,clk,clr,read,write);
parameter N=32;
parameter M=25;
input[N-1:0] A0,A1,A2,A3,A4,B0,B1,B2,B3,B4;
output[N-1:0] A0_out,A1_out,A2_out,A3_out,A4_out,B0_out,B1_out,B2_out,B3_out,B4_out;
input clk;
input[M-1:0] clr,read,write;
wire[N-1:0] B0_temp0,B1_temp0,B2_temp0,B3_temp0,B4_temp0;
wire[N-1:0] B0_temp1,B1_temp1,B2_temp1,B3_temp1,B4_temp1;
wire[N-1:0] B0_temp2,B1_temp2,B2_temp2,B3_temp2,B4_temp2;
wire[N-1:0] B0_temp3,B1_temp3,B2_temp3,B3_temp3,B4_temp3;
PE_layer PE_layer0(A0,B0,B1,B2,B3,B4,A0_out,B0_temp0,B1_temp0,B2_temp0,B3_temp0,B4_temp0,clk,clr[4:0],read[4:0],write[4:0]);
PE_layer PE_layer1(A1,B0_temp0,B1_temp0,B2_temp0,B3_temp0,B4_temp0,A1_out,B0_temp1,B1_temp1,B2_temp1,B3_temp1,B4_temp1,clk,clr[9:5],read[9:5],write[9:5]);
PE_layer PE_layer2(A2,B0_temp1,B1_temp1,B2_temp1,B3_temp1,B4_temp1,A2_out,B0_temp2,B1_temp2,B2_temp2,B3_temp2,B4_temp2,clk,clr[14:10],read[14:10],write[14:10]);
PE_layer PE_layer3(A3,B0_temp2,B1_temp2,B2_temp2,B3_temp2,B4_temp2,A3_out,B0_temp3,B1_temp3,B2_temp3,B3_temp3,B4_temp3,clk,clr[19:15],read[19:15],write[19:15]);
PE_layer PE_layer4(A4,B0_temp3,B1_temp3,B2_temp3,B3_temp3,B4_temp3,A4_out,B0_out,B1_out,B2_out,B3_out,B4_out,clk,clr[24:20],read[24:20],write[24:20]);
endmodule

Systolic_Array_test.v
module Systolic_Array_test;
parameter N=32;
parameter M=25;
reg[N-1:0] A0,A1,A2,A3,A4,B0,B1,B2,B3,B4;
wire[N-1:0] A0_out,A1_out,A2_out,A3_out,A4_out,B0_out,B1_out,B2_out,B3_out,B4_out;
reg clk;
reg[M-1:0] clr,read,write;
reg[N-1:0] regA[0:44];
reg[N-1:0] regB[0:44];
integer i;
Systolic_Array DUT(A0,A1,A2,A3,A4,B0,B1,B2,B3,B4,A0_out,A1_out,A2_out,A3_out,A4_out,B0_out,B1_out,B2_out,B3_out,B4_out,clk,clr,read,write);
initial begin
    clk=0;
    clr={25{1'b1}};
    read=25'b0;
    write=25'b0;
    $readmemb("/home/tharunsai/Documents/Project/code/Systolic-Array-main/A.txt",regA);
    $readmemb("/home/tharunsai/Documents/Project/code/Systolic-Array-main/B.txt",regB);
    #10 clr=25'b0;
    #500 $finish;
end
initial begin
    for(i=0;i<9;i=i+1)begin
    #10  A0=regA[i*5+0];
      A1=regA[i*5+1];
      A2=regA[i*5+2];
      A3=regA[i*5+3];
      A4=regA[i*5+4];
      B0=regB[i*5+0];
      B1=regB[i*5+1];
      B2=regB[i*5+2];
      B3=regB[i*5+3];
      B4=regB[i*5+4];
    end
end
always #5 clk=~clk;
initial begin
    $dumpfile("Systolic_Array_test.vcd");
    $dumpvars(0,Systolic_Array_test);
end
endmodule

Systolic_Array_test.vcd
$date
	Tue Sep 20 10:36:22 2022
$end
$version
	Icarus Verilog
$end
$timescale
	1s
$end
$scope module Systolic_Array_test $end
$var wire 32 ! B4_out [31:0] $end
$var wire 32 " B3_out [31:0] $end
$var wire 32 # B2_out [31:0] $end
$var wire 32 $ B1_out [31:0] $end
$var wire 32 % B0_out [31:0] $end
$var wire 32 & A4_out [31:0] $end
$var wire 32 ' A3_out [31:0] $end
$var wire 32 ( A2_out [31:0] $end
$var wire 32 ) A1_out [31:0] $end
$var wire 32 * A0_out [31:0] $end
$var reg 32 + A0 [31:0] $end
$var reg 32 , A1 [31:0] $end
$var reg 32 - A2 [31:0] $end
$var reg 32 . A3 [31:0] $end
$var reg 32 / A4 [31:0] $end
$var reg 32 0 B0 [31:0] $end
$var reg 32 1 B1 [31:0] $end
$var reg 32 2 B2 [31:0] $end
$var reg 32 3 B3 [31:0] $end
$var reg 32 4 B4 [31:0] $end
$var reg 1 5 clk $end
$var reg 25 6 clr [24:0] $end
$var reg 25 7 read [24:0] $end
$var reg 25 8 write [24:0] $end
$var integer 32 9 i [31:0] $end
$scope module DUT $end
$var wire 32 : A0 [31:0] $end
$var wire 32 ; A1 [31:0] $end
$var wire 32 < A2 [31:0] $end
$var wire 32 = A3 [31:0] $end
$var wire 32 > A4 [31:0] $end
$var wire 32 ? B0 [31:0] $end
$var wire 32 @ B1 [31:0] $end
$var wire 32 A B2 [31:0] $end
$var wire 32 B B3 [31:0] $end
$var wire 32 C B4 [31:0] $end
$var wire 1 5 clk $end
$var wire 25 D clr [24:0] $end
$var wire 25 E read [24:0] $end
$var wire 25 F write [24:0] $end
$var wire 32 G B4_temp3 [31:0] $end
$var wire 32 H B4_temp2 [31:0] $end
$var wire 32 I B4_temp1 [31:0] $end
$var wire 32 J B4_temp0 [31:0] $end
$var wire 32 K B4_out [31:0] $end
$var wire 32 L B3_temp3 [31:0] $end
$var wire 32 M B3_temp2 [31:0] $end
$var wire 32 N B3_temp1 [31:0] $end
$var wire 32 O B3_temp0 [31:0] $end
$var wire 32 P B3_out [31:0] $end
$var wire 32 Q B2_temp3 [31:0] $end
$var wire 32 R B2_temp2 [31:0] $end
$var wire 32 S B2_temp1 [31:0] $end
$var wire 32 T B2_temp0 [31:0] $end
$var wire 32 U B2_out [31:0] $end
$var wire 32 V B1_temp3 [31:0] $end
$var wire 32 W B1_temp2 [31:0] $end
$var wire 32 X B1_temp1 [31:0] $end
$var wire 32 Y B1_temp0 [31:0] $end
$var wire 32 Z B1_out [31:0] $end
$var wire 32 [ B0_temp3 [31:0] $end
$var wire 32 \ B0_temp2 [31:0] $end
$var wire 32 ] B0_temp1 [31:0] $end
$var wire 32 ^ B0_temp0 [31:0] $end
$var wire 32 _ B0_out [31:0] $end
$var wire 32 ` A4_out [31:0] $end
$var wire 32 a A3_out [31:0] $end
$var wire 32 b A2_out [31:0] $end
$var wire 32 c A1_out [31:0] $end
$var wire 32 d A0_out [31:0] $end
$scope module PE_layer0 $end
$var wire 32 e A0 [31:0] $end
$var wire 32 f B0 [31:0] $end
$var wire 32 g B1 [31:0] $end
$var wire 32 h B2 [31:0] $end
$var wire 32 i B3 [31:0] $end
$var wire 32 j B4 [31:0] $end
$var wire 1 5 clk $end
$var wire 5 k clr [4:0] $end
$var wire 5 l read [4:0] $end
$var wire 5 m write [4:0] $end
$var wire 32 n B4_out [31:0] $end
$var wire 32 o B3_out [31:0] $end
$var wire 32 p B2_out [31:0] $end
$var wire 32 q B1_out [31:0] $end
$var wire 32 r B0_out [31:0] $end
$var wire 32 s A0_temp3 [31:0] $end
$var wire 32 t A0_temp2 [31:0] $end
$var wire 32 u A0_temp1 [31:0] $end
$var wire 32 v A0_temp0 [31:0] $end
$var wire 32 w A0_out [31:0] $end
$scope module PE0 $end
$var wire 32 x A [31:0] $end
$var wire 32 y B [31:0] $end
$var wire 1 5 clk $end
$var wire 1 z clr $end
$var wire 1 { read $end
$var wire 1 | write $end
$var reg 32 } Acc [31:0] $end
$var reg 32 ~ Aout [31:0] $end
$var reg 32 !" Bout [31:0] $end
$upscope $end
$scope module PE1 $end
$var wire 32 "" A [31:0] $end
$var wire 32 #" B [31:0] $end
$var wire 1 5 clk $end
$var wire 1 $" clr $end
$var wire 1 %" read $end
$var wire 1 &" write $end
$var reg 32 '" Acc [31:0] $end
$var reg 32 (" Aout [31:0] $end
$var reg 32 )" Bout [31:0] $end
$upscope $end
$scope module PE2 $end
$var wire 32 *" A [31:0] $end
$var wire 32 +" B [31:0] $end
$var wire 1 5 clk $end
$var wire 1 ," clr $end
$var wire 1 -" read $end
$var wire 1 ." write $end
$var reg 32 /" Acc [31:0] $end
$var reg 32 0" Aout [31:0] $end
$var reg 32 1" Bout [31:0] $end
$upscope $end
$scope module PE3 $end
$var wire 32 2" A [31:0] $end
$var wire 32 3" B [31:0] $end
$var wire 1 5 clk $end
$var wire 1 4" clr $end
$var wire 1 5" read $end
$var wire 1 6" write $end
$var reg 32 7" Acc [31:0] $end
$var reg 32 8" Aout [31:0] $end
$var reg 32 9" Bout [31:0] $end
$upscope $end
$scope module PE4 $end
$var wire 32 :" A [31:0] $end
$var wire 32 ;" B [31:0] $end
$var wire 1 5 clk $end
$var wire 1 <" clr $end
$var wire 1 =" read $end
$var wire 1 >" write $end
$var reg 32 ?" Acc [31:0] $end
$var reg 32 @" Aout [31:0] $end
$var reg 32 A" Bout [31:0] $end
$upscope $end
$upscope $end
$scope module PE_layer1 $end
$var wire 32 B" A0 [31:0] $end
$var wire 32 C" B0 [31:0] $end
$var wire 32 D" B1 [31:0] $end
$var wire 32 E" B2 [31:0] $end
$var wire 32 F" B3 [31:0] $end
$var wire 32 G" B4 [31:0] $end
$var wire 1 5 clk $end
$var wire 5 H" clr [4:0] $end
$var wire 5 I" read [4:0] $end
$var wire 5 J" write [4:0] $end
$var wire 32 K" B4_out [31:0] $end
$var wire 32 L" B3_out [31:0] $end
$var wire 32 M" B2_out [31:0] $end
$var wire 32 N" B1_out [31:0] $end
$var wire 32 O" B0_out [31:0] $end
$var wire 32 P" A0_temp3 [31:0] $end
$var wire 32 Q" A0_temp2 [31:0] $end
$var wire 32 R" A0_temp1 [31:0] $end
$var wire 32 S" A0_temp0 [31:0] $end
$var wire 32 T" A0_out [31:0] $end
$scope module PE0 $end
$var wire 32 U" A [31:0] $end
$var wire 32 V" B [31:0] $end
$var wire 1 5 clk $end
$var wire 1 W" clr $end
$var wire 1 X" read $end
$var wire 1 Y" write $end
$var reg 32 Z" Acc [31:0] $end
$var reg 32 [" Aout [31:0] $end
$var reg 32 \" Bout [31:0] $end
$upscope $end
$scope module PE1 $end
$var wire 32 ]" A [31:0] $end
$var wire 32 ^" B [31:0] $end
$var wire 1 5 clk $end
$var wire 1 _" clr $end
$var wire 1 `" read $end
$var wire 1 a" write $end
$var reg 32 b" Acc [31:0] $end
$var reg 32 c" Aout [31:0] $end
$var reg 32 d" Bout [31:0] $end
$upscope $end
$scope module PE2 $end
$var wire 32 e" A [31:0] $end
$var wire 32 f" B [31:0] $end
$var wire 1 5 clk $end
$var wire 1 g" clr $end
$var wire 1 h" read $end
$var wire 1 i" write $end
$var reg 32 j" Acc [31:0] $end
$var reg 32 k" Aout [31:0] $end
$var reg 32 l" Bout [31:0] $end
$upscope $end
$scope module PE3 $end
$var wire 32 m" A [31:0] $end
$var wire 32 n" B [31:0] $end
$var wire 1 5 clk $end
$var wire 1 o" clr $end
$var wire 1 p" read $end
$var wire 1 q" write $end
$var reg 32 r" Acc [31:0] $end
$var reg 32 s" Aout [31:0] $end
$var reg 32 t" Bout [31:0] $end
$upscope $end
$scope module PE4 $end
$var wire 32 u" A [31:0] $end
$var wire 32 v" B [31:0] $end
$var wire 1 5 clk $end
$var wire 1 w" clr $end
$var wire 1 x" read $end
$var wire 1 y" write $end
$var reg 32 z" Acc [31:0] $end
$var reg 32 {" Aout [31:0] $end
$var reg 32 |" Bout [31:0] $end
$upscope $end
$upscope $end
$scope module PE_layer2 $end
$var wire 32 }" A0 [31:0] $end
$var wire 32 ~" B0 [31:0] $end
$var wire 32 !# B1 [31:0] $end
$var wire 32 "# B2 [31:0] $end
$var wire 32 ## B3 [31:0] $end
$var wire 32 $# B4 [31:0] $end
$var wire 1 5 clk $end
$var wire 5 %# clr [4:0] $end
$var wire 5 &# read [4:0] $end
$var wire 5 '# write [4:0] $end
$var wire 32 (# B4_out [31:0] $end
$var wire 32 )# B3_out [31:0] $end
$var wire 32 *# B2_out [31:0] $end
$var wire 32 +# B1_out [31:0] $end
$var wire 32 ,# B0_out [31:0] $end
$var wire 32 -# A0_temp3 [31:0] $end
$var wire 32 .# A0_temp2 [31:0] $end
$var wire 32 /# A0_temp1 [31:0] $end
$var wire 32 0# A0_temp0 [31:0] $end
$var wire 32 1# A0_out [31:0] $end
$scope module PE0 $end
$var wire 32 2# A [31:0] $end
$var wire 32 3# B [31:0] $end
$var wire 1 5 clk $end
$var wire 1 4# clr $end
$var wire 1 5# read $end
$var wire 1 6# write $end
$var reg 32 7# Acc [31:0] $end
$var reg 32 8# Aout [31:0] $end
$var reg 32 9# Bout [31:0] $end
$upscope $end
$scope module PE1 $end
$var wire 32 :# A [31:0] $end
$var wire 32 ;# B [31:0] $end
$var wire 1 5 clk $end
$var wire 1 <# clr $end
$var wire 1 =# read $end
$var wire 1 ># write $end
$var reg 32 ?# Acc [31:0] $end
$var reg 32 @# Aout [31:0] $end
$var reg 32 A# Bout [31:0] $end
$upscope $end
$scope module PE2 $end
$var wire 32 B# A [31:0] $end
$var wire 32 C# B [31:0] $end
$var wire 1 5 clk $end
$var wire 1 D# clr $end
$var wire 1 E# read $end
$var wire 1 F# write $end
$var reg 32 G# Acc [31:0] $end
$var reg 32 H# Aout [31:0] $end
$var reg 32 I# Bout [31:0] $end
$upscope $end
$scope module PE3 $end
$var wire 32 J# A [31:0] $end
$var wire 32 K# B [31:0] $end
$var wire 1 5 clk $end
$var wire 1 L# clr $end
$var wire 1 M# read $end
$var wire 1 N# write $end
$var reg 32 O# Acc [31:0] $end
$var reg 32 P# Aout [31:0] $end
$var reg 32 Q# Bout [31:0] $end
$upscope $end
$scope module PE4 $end
$var wire 32 R# A [31:0] $end
$var wire 32 S# B [31:0] $end
$var wire 1 5 clk $end
$var wire 1 T# clr $end
$var wire 1 U# read $end
$var wire 1 V# write $end
$var reg 32 W# Acc [31:0] $end
$var reg 32 X# Aout [31:0] $end
$var reg 32 Y# Bout [31:0] $end
$upscope $end
$upscope $end
$scope module PE_layer3 $end
$var wire 32 Z# A0 [31:0] $end
$var wire 32 [# B0 [31:0] $end
$var wire 32 \# B1 [31:0] $end
$var wire 32 ]# B2 [31:0] $end
$var wire 32 ^# B3 [31:0] $end
$var wire 32 _# B4 [31:0] $end
$var wire 1 5 clk $end
$var wire 5 `# clr [4:0] $end
$var wire 5 a# read [4:0] $end
$var wire 5 b# write [4:0] $end
$var wire 32 c# B4_out [31:0] $end
$var wire 32 d# B3_out [31:0] $end
$var wire 32 e# B2_out [31:0] $end
$var wire 32 f# B1_out [31:0] $end
$var wire 32 g# B0_out [31:0] $end
$var wire 32 h# A0_temp3 [31:0] $end
$var wire 32 i# A0_temp2 [31:0] $end
$var wire 32 j# A0_temp1 [31:0] $end
$var wire 32 k# A0_temp0 [31:0] $end
$var wire 32 l# A0_out [31:0] $end
$scope module PE0 $end
$var wire 32 m# A [31:0] $end
$var wire 32 n# B [31:0] $end
$var wire 1 5 clk $end
$var wire 1 o# clr $end
$var wire 1 p# read $end
$var wire 1 q# write $end
$var reg 32 r# Acc [31:0] $end
$var reg 32 s# Aout [31:0] $end
$var reg 32 t# Bout [31:0] $end
$upscope $end
$scope module PE1 $end
$var wire 32 u# A [31:0] $end
$var wire 32 v# B [31:0] $end
$var wire 1 5 clk $end
$var wire 1 w# clr $end
$var wire 1 x# read $end
$var wire 1 y# write $end
$var reg 32 z# Acc [31:0] $end
$var reg 32 {# Aout [31:0] $end
$var reg 32 |# Bout [31:0] $end
$upscope $end
$scope module PE2 $end
$var wire 32 }# A [31:0] $end
$var wire 32 ~# B [31:0] $end
$var wire 1 5 clk $end
$var wire 1 !$ clr $end
$var wire 1 "$ read $end
$var wire 1 #$ write $end
$var reg 32 $$ Acc [31:0] $end
$var reg 32 %$ Aout [31:0] $end
$var reg 32 &$ Bout [31:0] $end
$upscope $end
$scope module PE3 $end
$var wire 32 '$ A [31:0] $end
$var wire 32 ($ B [31:0] $end
$var wire 1 5 clk $end
$var wire 1 )$ clr $end
$var wire 1 *$ read $end
$var wire 1 +$ write $end
$var reg 32 ,$ Acc [31:0] $end
$var reg 32 -$ Aout [31:0] $end
$var reg 32 .$ Bout [31:0] $end
$upscope $end
$scope module PE4 $end
$var wire 32 /$ A [31:0] $end
$var wire 32 0$ B [31:0] $end
$var wire 1 5 clk $end
$var wire 1 1$ clr $end
$var wire 1 2$ read $end
$var wire 1 3$ write $end
$var reg 32 4$ Acc [31:0] $end
$var reg 32 5$ Aout [31:0] $end
$var reg 32 6$ Bout [31:0] $end
$upscope $end
$upscope $end
$scope module PE_layer4 $end
$var wire 32 7$ A0 [31:0] $end
$var wire 32 8$ B0 [31:0] $end
$var wire 32 9$ B1 [31:0] $end
$var wire 32 :$ B2 [31:0] $end
$var wire 32 ;$ B3 [31:0] $end
$var wire 32 <$ B4 [31:0] $end
$var wire 1 5 clk $end
$var wire 5 =$ clr [4:0] $end
$var wire 5 >$ read [4:0] $end
$var wire 5 ?$ write [4:0] $end
$var wire 32 @$ B4_out [31:0] $end
$var wire 32 A$ B3_out [31:0] $end
$var wire 32 B$ B2_out [31:0] $end
$var wire 32 C$ B1_out [31:0] $end
$var wire 32 D$ B0_out [31:0] $end
$var wire 32 E$ A0_temp3 [31:0] $end
$var wire 32 F$ A0_temp2 [31:0] $end
$var wire 32 G$ A0_temp1 [31:0] $end
$var wire 32 H$ A0_temp0 [31:0] $end
$var wire 32 I$ A0_out [31:0] $end
$scope module PE0 $end
$var wire 32 J$ A [31:0] $end
$var wire 32 K$ B [31:0] $end
$var wire 1 5 clk $end
$var wire 1 L$ clr $end
$var wire 1 M$ read $end
$var wire 1 N$ write $end
$var reg 32 O$ Acc [31:0] $end
$var reg 32 P$ Aout [31:0] $end
$var reg 32 Q$ Bout [31:0] $end
$upscope $end
$scope module PE1 $end
$var wire 32 R$ A [31:0] $end
$var wire 32 S$ B [31:0] $end
$var wire 1 5 clk $end
$var wire 1 T$ clr $end
$var wire 1 U$ read $end
$var wire 1 V$ write $end
$var reg 32 W$ Acc [31:0] $end
$var reg 32 X$ Aout [31:0] $end
$var reg 32 Y$ Bout [31:0] $end
$upscope $end
$scope module PE2 $end
$var wire 32 Z$ A [31:0] $end
$var wire 32 [$ B [31:0] $end
$var wire 1 5 clk $end
$var wire 1 \$ clr $end
$var wire 1 ]$ read $end
$var wire 1 ^$ write $end
$var reg 32 _$ Acc [31:0] $end
$var reg 32 `$ Aout [31:0] $end
$var reg 32 a$ Bout [31:0] $end
$upscope $end
$scope module PE3 $end
$var wire 32 b$ A [31:0] $end
$var wire 32 c$ B [31:0] $end
$var wire 1 5 clk $end
$var wire 1 d$ clr $end
$var wire 1 e$ read $end
$var wire 1 f$ write $end
$var reg 32 g$ Acc [31:0] $end
$var reg 32 h$ Aout [31:0] $end
$var reg 32 i$ Bout [31:0] $end
$upscope $end
$scope module PE4 $end
$var wire 32 j$ A [31:0] $end
$var wire 32 k$ B [31:0] $end
$var wire 1 5 clk $end
$var wire 1 l$ clr $end
$var wire 1 m$ read $end
$var wire 1 n$ write $end
$var reg 32 o$ Acc [31:0] $end
$var reg 32 p$ Aout [31:0] $end
$var reg 32 q$ Bout [31:0] $end
$upscope $end
$upscope $end
$upscope $end
$upscope $end
$enddefinitions $end
#0
$dumpvars
bx q$
bx p$
bx o$
0n$
0m$
1l$
bx k$
bx j$
bx i$
bx h$
bx g$
0f$
0e$
1d$
bx c$
bx b$
bx a$
bx `$
bx _$
0^$
0]$
1\$
bx [$
bx Z$
bx Y$
bx X$
bx W$
0V$
0U$
1T$
bx S$
bx R$
bx Q$
bx P$
bx O$
0N$
0M$
1L$
bx K$
bx J$
bx I$
bx H$
bx G$
bx F$
bx E$
bx D$
bx C$
bx B$
bx A$
bx @$
b0 ?$
b0 >$
b11111 =$
bx <$
bx ;$
bx :$
bx 9$
bx 8$
bx 7$
bx 6$
bx 5$
bx 4$
03$
02$
11$
bx 0$
bx /$
bx .$
bx -$
bx ,$
0+$
0*$
1)$
bx ($
bx '$
bx &$
bx %$
bx $$
0#$
0"$
1!$
bx ~#
bx }#
bx |#
bx {#
bx z#
0y#
0x#
1w#
bx v#
bx u#
bx t#
bx s#
bx r#
0q#
0p#
1o#
bx n#
bx m#
bx l#
bx k#
bx j#
bx i#
bx h#
bx g#
bx f#
bx e#
bx d#
bx c#
b0 b#
b0 a#
b11111 `#
bx _#
bx ^#
bx ]#
bx \#
bx [#
bx Z#
bx Y#
bx X#
bx W#
0V#
0U#
1T#
bx S#
bx R#
bx Q#
bx P#
bx O#
0N#
0M#
1L#
bx K#
bx J#
bx I#
bx H#
bx G#
0F#
0E#
1D#
bx C#
bx B#
bx A#
bx @#
bx ?#
0>#
0=#
1<#
bx ;#
bx :#
bx 9#
bx 8#
bx 7#
06#
05#
14#
bx 3#
bx 2#
bx 1#
bx 0#
bx /#
bx .#
bx -#
bx ,#
bx +#
bx *#
bx )#
bx (#
b0 '#
b0 &#
b11111 %#
bx $#
bx ##
bx "#
bx !#
bx ~"
bx }"
bx |"
bx {"
bx z"
0y"
0x"
1w"
bx v"
bx u"
bx t"
bx s"
bx r"
0q"
0p"
1o"
bx n"
bx m"
bx l"
bx k"
bx j"
0i"
0h"
1g"
bx f"
bx e"
bx d"
bx c"
bx b"
0a"
0`"
1_"
bx ^"
bx ]"
bx \"
bx ["
bx Z"
0Y"
0X"
1W"
bx V"
bx U"
bx T"
bx S"
bx R"
bx Q"
bx P"
bx O"
bx N"
bx M"
bx L"
bx K"
b0 J"
b0 I"
b11111 H"
bx G"
bx F"
bx E"
bx D"
bx C"
bx B"
bx A"
bx @"
bx ?"
0>"
0="
1<"
bx ;"
bx :"
bx 9"
bx 8"
bx 7"
06"
05"
14"
bx 3"
bx 2"
bx 1"
bx 0"
bx /"
0."
0-"
1,"
bx +"
bx *"
bx )"
bx ("
bx '"
0&"
0%"
1$"
bx #"
bx ""
bx !"
bx ~
bx }
0|
0{
1z
bx y
bx x
bx w
bx v
bx u
bx t
bx s
bx r
bx q
bx p
bx o
bx n
b0 m
b0 l
b11111 k
bx j
bx i
bx h
bx g
bx f
bx e
bx d
bx c
bx b
bx a
bx `
bx _
bx ^
bx ]
bx \
bx [
bx Z
bx Y
bx X
bx W
bx V
bx U
bx T
bx S
bx R
bx Q
bx P
bx O
bx N
bx M
bx L
bx K
bx J
bx I
bx H
bx G
b0 F
b0 E
b1111111111111111111111111 D
bx C
bx B
bx A
bx @
bx ?
bx >
bx =
bx <
bx ;
bx :
b0 9
b0 8
b0 7
b1111111111111111111111111 6
05
bx 4
bx 3
bx 2
bx 1
bx 0
bx /
bx .
bx -
bx ,
bx +
bx *
bx )
bx (
bx '
bx &
bx %
bx $
bx #
bx "
bx !
$end
#5
b0 ^
b0 r
b0 !"
b0 C"
b0 V"
b0 v
b0 ~
b0 ""
b0 }
b0 Y
b0 q
b0 )"
b0 D"
b0 ^"
b0 u
b0 ("
b0 *"
b0 '"
b0 T
b0 p
b0 1"
b0 E"
b0 f"
b0 t
b0 0"
b0 2"
b0 /"
b0 O
b0 o
b0 9"
b0 F"
b0 n"
b0 s
b0 8"
b0 :"
b0 7"
b0 J
b0 n
b0 A"
b0 G"
b0 v"
b0 *
b0 d
b0 w
b0 @"
b0 ?"
b0 ]
b0 O"
b0 \"
b0 ~"
b0 3#
b0 S"
b0 ["
b0 ]"
b0 Z"
b0 X
b0 N"
b0 d"
b0 !#
b0 ;#
b0 R"
b0 c"
b0 e"
b0 b"
b0 S
b0 M"
b0 l"
b0 "#
b0 C#
b0 Q"
b0 k"
b0 m"
b0 j"
b0 N
b0 L"
b0 t"
b0 ##
b0 K#
b0 P"
b0 s"
b0 u"
b0 r"
b0 I
b0 K"
b0 |"
b0 $#
b0 S#
b0 )
b0 c
b0 T"
b0 {"
b0 z"
b0 \
b0 ,#
b0 9#
b0 [#
b0 n#
b0 0#
b0 8#
b0 :#
b0 7#
b0 W
b0 +#
b0 A#
b0 \#
b0 v#
b0 /#
b0 @#
b0 B#
b0 ?#
b0 R
b0 *#
b0 I#
b0 ]#
b0 ~#
b0 .#
b0 H#
b0 J#
b0 G#
b0 M
b0 )#
b0 Q#
b0 ^#
b0 ($
b0 -#
b0 P#
b0 R#
b0 O#
b0 H
b0 (#
b0 Y#
b0 _#
b0 0$
b0 (
b0 b
b0 1#
b0 X#
b0 W#
b0 [
b0 g#
b0 t#
b0 8$
b0 K$
b0 k#
b0 s#
b0 u#
b0 r#
b0 V
b0 f#
b0 |#
b0 9$
b0 S$
b0 j#
b0 {#
b0 }#
b0 z#
b0 Q
b0 e#
b0 &$
b0 :$
b0 [$
b0 i#
b0 %$
b0 '$
b0 $$
b0 L
b0 d#
b0 .$
b0 ;$
b0 c$
b0 h#
b0 -$
b0 /$
b0 ,$
b0 G
b0 c#
b0 6$
b0 <$
b0 k$
b0 '
b0 a
b0 l#
b0 5$
b0 4$
b0 %
b0 _
b0 D$
b0 Q$
b0 H$
b0 P$
b0 R$
b0 O$
b0 $
b0 Z
b0 C$
b0 Y$
b0 G$
b0 X$
b0 Z$
b0 W$
b0 #
b0 U
b0 B$
b0 a$
b0 F$
b0 `$
b0 b$
b0 _$
b0 "
b0 P
b0 A$
b0 i$
b0 E$
b0 h$
b0 j$
b0 g$
b0 !
b0 K
b0 @$
b0 q$
b0 &
b0 `
b0 I$
b0 p$
b0 o$
15
#10
0z
0$"
0,"
04"
0<"
0W"
0_"
0g"
0o"
0w"
04#
0<#
0D#
0L#
0T#
0o#
0w#
0!$
0)$
01$
0L$
0T$
0\$
0d$
0l$
b0 k
b0 H"
b0 %#
b0 `#
b0 =$
05
b1 9
b0 4
b0 C
b0 j
b0 ;"
b0 3
b0 B
b0 i
b0 3"
b0 2
b0 A
b0 h
b0 +"
b0 1
b0 @
b0 g
b0 #"
b110 0
b110 ?
b110 f
b110 y
b0 /
b0 >
b0 7$
b0 J$
b0 .
b0 =
b0 Z#
b0 m#
b0 -
b0 <
b0 }"
b0 2#
b0 ,
b0 ;
b0 B"
b0 U"
b1001 +
b1001 :
b1001 e
b1001 x
b0 6
b0 D
#15
b110 ^
b110 r
b110 !"
b110 C"
b110 V"
b1001 v
b1001 ~
b1001 ""
b110110 }
15
#20
05
b10 9
b11 1
b11 @
b11 g
b11 #"
b1 0
b1 ?
b1 f
b1 y
b100 ,
b100 ;
b100 B"
b100 U"
b1000 +
b1000 :
b1000 e
b1000 x
#25
b1 ^
b1 r
b1 !"
b1 C"
b1 V"
b1000 v
b1000 ~
b1000 ""
b111110 }
b11 Y
b11 q
b11 )"
b11 D"
b11 ^"
b1001 u
b1001 ("
b1001 *"
b11011 '"
b110 ]
b110 O"
b110 \"
b110 ~"
b110 3#
b100 S"
b100 ["
b100 ]"
b11000 Z"
15
#30
05
b11 9
b110 2
b110 A
b110 h
b110 +"
b100 1
b100 @
b100 g
b100 #"
b0 0
b0 ?
b0 f
b0 y
b1000 -
b1000 <
b1000 }"
b1000 2#
b110 ,
b110 ;
b110 B"
b110 U"
b1001 +
b1001 :
b1001 e
b1001 x
#35
b110 \
b110 ,#
b110 9#
b110 [#
b110 n#
b1000 0#
b1000 8#
b1000 :#
b110000 7#
b11 X
b11 N"
b11 d"
b11 !#
b11 ;#
b100 R"
b100 c"
b100 e"
b1100 b"
b1 ]
b1 O"
b1 \"
b1 ~"
b1 3#
b110 S"
b110 ["
b110 ]"
b11110 Z"
b110 T
b110 p
b110 1"
b110 E"
b110 f"
b1001 t
b1001 0"
b1001 2"
b110110 /"
b100 Y
b100 q
b100 )"
b100 D"
b100 ^"
b1000 u
b1000 ("
b1000 *"
b111011 '"
b0 ^
b0 r
b0 !"
b0 C"
b0 V"
b1001 v
b1001 ~
b1001 ""
15
#40
05
b100 9
b1000 3
b1000 B
b1000 i
b1000 3"
b1000 2
b1000 A
b1000 h
b1000 +"
b1001 1
b1001 @
b1001 g
b1001 #"
b101 0
b101 ?
b101 f
b101 y
b111 .
b111 =
b111 Z#
b111 m#
b111 ,
b111 ;
b111 B"
b111 U"
b10 +
b10 :
b10 e
b10 x
